recruiter_app/__init__.py
recruiter_app/app.py
recruiter_app/config/config.json
recruiter_app/config/gh_skills_count.csv
recruiter_app/config/rd_skills_count.csv
recruiter_app/config/so_skills_count.csv
recruiter_app/elt_app/__init__.py
recruiter_app/elt_app/main.py
recruiter_app/elt_app/api/__init__.py
recruiter_app/elt_app/api/github.py
recruiter_app/elt_app/api/reddit.py
recruiter_app/elt_app/api/stackoverflow.py
recruiter_app/elt_app/collections/__init__.py
recruiter_app/elt_app/collections/candidate_ratings.py
recruiter_app/elt_app/collections/evaluate_candidates.py
recruiter_app/elt_app/collections/gh_users_details.py
recruiter_app/elt_app/collections/job_descr_config.py
recruiter_app/elt_app/collections/reddit_user_props.py
recruiter_app/elt_app/collections/so_users_details.py
recruiter_app/elt_app/service/__init__.py
recruiter_app/elt_app/service/exec_recipe.py
recruiter_app/elt_app/service/merge_data.py
recruiter_app/elt_app/service/mongo.py
recruiter_app/elt_app/service/rating_prep.py
recruiter_app/elt_app/service/rating_recipes.py
recruiter_app/notification/__init__.py
recruiter_app/notification/notification_app.py
recruiter_app/utilities/__init__.py
recruiter_app/utilities/helpers.py
recruiter_app-1.0.5.dist-info/METADATA
recruiter_app-1.0.5.dist-info/WHEEL
recruiter_app-1.0.5.dist-info/top_level.txt
recruiter_app-1.0.5.dist-info/RECORD
