Metadata-Version: 2.1
Name: recruiter-app
Version: 1.0.5
Summary: This is hush hush recruiter app
Author-email: prabhu <prabhupad@somwwhe.com>
Classifier: Programming Language :: Python :: 3
Classifier: License :: OSI Approved :: MIT License
Classifier: Operating System :: OS Independent
Requires-Python: >=3.7
